{
  "project_info": {
    "project_number": "911927278113",
    "firebase_url": "https://wedproject-d750d.firebaseio.com",
    "project_id": "wedproject-d750d",
    "storage_bucket": "wedproject-d750d.appspot.com"
  },
  "client": [
    {
      "client_info": {
        "mobilesdk_app_id": "1:911927278113:android:eae82a398409f151",
        "android_client_info": {
          "package_name": "com.easytoquit.easytoquit_casemanager"
        }
      },
      "oauth_client": [
        {
          "client_id": "911927278113-5vmv1a2bf1vfemg9n2bkqlptujjs9ii4.apps.googleusercontent.com",
          "client_type": 1,
          "android_info": {
            "package_name": "com.easytoquit.easytoquit_casemanager",
            "certificate_hash": "77dc8d10805afeecc05c7774e77404eb0b0ca6e9"
          }
        },
        {
          "client_id": "911927278113-p4nvt81bekg7qmpftkh65kj39073j5d1.apps.googleusercontent.com",
          "client_type": 3
        }
      ],
      "api_key": [
        {
          "current_key": "AIzaSyCl8eFxglay7nKPhLW1k0bCbPG7JXdX87s"
        }
      ],
      "services": {
        "analytics_service": {
          "status": 1
        },
        "appinvite_service": {
          "status": 2,
          "other_platform_oauth_client": [
            {
              "client_id": "911927278113-p4nvt81bekg7qmpftkh65kj39073j5d1.apps.googleusercontent.com",
              "client_type": 3
            }
          ]
        },
        "ads_service": {
          "status": 2
        }
      }
    }
  ],
  "configuration_version": "1"
}